__init__.py
voicen/__init__.py
voicen/vcnclient.py
voicen/classes/__init__.py
voicen/classes/account.py
voicen/classes/job.py
voicen/classes/job_status.py
voicen/classes/payment.py
voicen/classes/payment_type.py
voicen/classes/subscription.py
voicen/classes/subscription_status.py
voicen/classes/transcription.py
voicen/classes/word.py
voicen-1.0.3.dist-info/DESCRIPTION.rst
voicen-1.0.3.dist-info/METADATA
voicen-1.0.3.dist-info/RECORD
voicen-1.0.3.dist-info/WHEEL
voicen-1.0.3.dist-info/metadata.json
voicen-1.0.3.dist-info/top_level.txt
