Metadata-Version: 2.0
Name: voicen
Version: 1.0.3
Summary: The python SDK developed by Voicen allows customers to use speech-to-text service of Voicen.
Home-page: https://github.com/voicen-llc/voicen-python-sdk
Author: Voicen LLC
Author-email: info@voicen.com
License: MIT license
Keywords: voicen
Platform: UNKNOWN
Classifier: License :: OSI Approved :: MIT License
Classifier: Operating System :: OS Independent
Classifier: Programming Language :: Python :: 2
Classifier: Programming Language :: Python :: 2.7
Classifier: Programming Language :: Python :: 3
Classifier: Programming Language :: Python :: 3.4
Classifier: Programming Language :: Python :: 3.5
Classifier: Programming Language :: Python :: 3.6
Classifier: Programming Language :: Python :: 3.7
Requires-Dist: requests (==2.21.0)
Requires-Dist: enum34 (==1.1.6)
